turbine/__init__.py
turbine/turbine.py
turbine/types.py
turbine_sdk-0.0.2.dist-info/METADATA
turbine_sdk-0.0.2.dist-info/WHEEL
turbine_sdk-0.0.2.dist-info/RECORD
