Metadata-Version: 2.1
Name: turbine-sdk
Version: 0.0.2
Summary: Python SDK for Turbine
Author: Ankit Solanki
Author-email: ankit@useturbine.com
Requires-Python: >=3.8,<4.0
Classifier: Programming Language :: Python :: 3
Classifier: Programming Language :: Python :: 3.8
Classifier: Programming Language :: Python :: 3.9
Classifier: Programming Language :: Python :: 3.10
Classifier: Programming Language :: Python :: 3.11
Requires-Dist: httpx (>=0.24.1,<0.25.0)
Requires-Dist: pydantic (>=2.3.0,<3.0.0)
